LICENSE
MANIFEST.in
README.md
requirements-dev.txt
requirements.txt
setup.py
restflow/__init__.py
restflow/__init__.pyc
restflow/base.py
restflow/base.pyc
restflow/client.py
restflow/client.pyc
restflow/config.py
restflow/config.pyc
restflow/hf3binding.py
restflow/hf3binding.pyc
restflow/hf3configs.py
restflow/hf3configs.pyc
restflow/hf3lint.py
restflow/hf3lint.pyc
restflow/resultfunc.py
restflow/resultfunc.pyc
restflow/server.py
restflow/server.pyc
restflow/vtkfunctions.py
restflow.egg-info/PKG-INFO
restflow.egg-info/SOURCES.txt
restflow.egg-info/dependency_links.txt
restflow.egg-info/not-zip-safe
restflow.egg-info/top_level.txt
share/run_restflow.py