Metadata-Version: 1.1
Name: restflow
Version: 0.8-beta
Summary: Interactive Hiflow3 Simulation an HTTP Request far away
Home-page: http://github.com/CognitionGuidedSurgery/restflow
Author: ['Alexander Weigl', 'Nicolai Schoch']
Author-email: uiduw@student.kit.edu
License: gpl3
Platform: UNKNOWN
Classifier: Development Status :: 3 - Alpha
Classifier: Environment :: Web Environment
Classifier: License :: OSI Approved :: GNU General Public License v3 (GPLv3)
Classifier: Operating System :: POSIX :: Linux
Classifier: Programming Language :: Python
Classifier: Framework :: Flask
Provides: restflow
